Workbook

Sheet Istruzioni
A1: Budget Familiare 2027
A3: 1. Apri il foglio Budget e sostituisci le categorie con le tue.
A4: 2. Scrivi il budget mensile nella colonna C, poi le spese reali mese per mese.
A5: 3. Il foglio Riepilogo calcola risparmio annuo e tasso di risparmio.
A7: Nessuna macro. Nessun dato inviato. Funziona in Excel, LibreOffice e Google Fogli.
A9: Licenza: uso personale e familiare. Non è consentita la rivendita del file.

Sheet Budget
A1: Budget Familiare 2027
A3: Categoria | B3: Tipo | C3: Budget mese | D3: Gen | E3: Feb | F3: Mar | G3: Apr | H3: Mag | I3: Giu | J3: Lug | K3: Ago | L3: Set | M3: Ott | N3: Nov | O3: Dic | P3: Totale anno | Q3: Media mese | R3: Delta vs budget
A4: Stipendio | B4: Entrata | C4: 2000 | D4: 0 | E4: 0 | F4: 0 | G4: 0 | H4: 0 | I4: 0 | J4: 0 | K4: 0 | L4: 0 | M4: 0 | N4: 0 | O4: 0 | P4: =SUM(D4:O4) | Q4: =IFERROR(AVERAGE(D4:O4),0) | R4: =P4-C4*12
A5: Altro reddito | B5: Entrata | C5: 0 | D5: 0 | E5: 0 | F5: 0 | G5: 0 | H5: 0 | I5: 0 | J5: 0 | K5: 0 | L5: 0 | M5: 0 | N5: 0 | O5: 0 | P5: =SUM(D5:O5) | Q5: =IFERROR(AVERAGE(D5:O5),0) | R5: =P5-C5*12
A6: TOTALE ENTRATE | C6: =SUM(C4:C5) | D6: =SUM(D4:D5) | E6: =SUM(E4:E5) | F6: =SUM(F4:F5) | G6: =SUM(G4:G5) | H6: =SUM(H4:H5) | I6: =SUM(I4:I5) | J6: =SUM(J4:J5) | ... O6: =SUM(O4:O5) | P6: =SUM(D6:O6) | Q6: =P6/12 | R6: =P6-C6*12
A7: Casa (affitto o mutuo) | B7: Uscita | C7: 700 | D7: 0 | E7: 0 | F7: 0 | G7: 0 | H7: 0 | I7: 0 | J7: 0 | K7: 0 | L7: 0 | M7: 0 | N7: 0 | O7: 0 | P7: =SUM(D7:O7) | Q7: =IFERROR(AVERAGE(D7:O7),0) | R7: =P7-C7*12
A8: Spesa alimentare | B8: Uscita | C8: 350 | D8: 0 | E8: 0 | F8: 0 | G8: 0 | H8: 0 | I8: 0 | J8: 0 | K8: 0 | L8: 0 | M8: 0 | N8: 0 | O8: 0 | P8: =SUM(D8:O8) | Q8: =IFERROR(AVERAGE(D8:O8),0) | R8: =P8-C8*12
A9: Trasporti | B9: Uscita | C9: 120 | D9: 0 | E9: 0 | F9: 0 | G9: 0 | H9: 0 | I9: 0 | J9: 0 | K9: 0 | L9: 0 | M9: 0 | N9: 0 | O9: 0 | P9: =SUM(D9:O9) | Q9: =IFERROR(AVERAGE(D9:O9),0) | R9: =P9-C9*12
A10: Bollette | B10: Uscita | C10: 150 | D10: 0 | E10: 0 | F10: 0 | G10: 0 | H10: 0 | I10: 0 | J10: 0 | K10: 0 | L10: 0 | M10: 0 | N10: 0 | O10: 0 | P10: =SUM(D10:O10) | Q10: =IFERROR(AVERAGE(D10:O10),0) | R10: =P10-C10*12
A11: Salute | B11: Uscita | C11: 60 | D11: 0 | E11: 0 | F11: 0 | G11: 0 | H11: 0 | I11: 0 | J11: 0 | K11: 0 | L11: 0 | M11: 0 | N11: 0 | O11: 0 | P11: =SUM(D11:O11) | Q11: =IFERROR(AVERAGE(D11:O11),0) | R11: =P11-C11*12
A12: Svago | B12: Uscita | C12: 120 | D12: 0 | E12: 0 | F12: 0 | G12: 0 | H12: 0 | I12: 0 | J12: 0 | K12: 0 | L12: 0 | M12: 0 | N12: 0 | O12: 0 | P12: =SUM(D12:O12) | Q12: =IFERROR(AVERAGE(D12:O12),0) | R12: =P12-C12*12
A13: Altre spese | B13: Uscita | C13: 100 | D13: 0 | E13: 0 | F13: 0 | G13: 0 | H13: 0 | I13: 0 | J13: 0 | K13: 0 | L13: 0 | M13: 0 | N13: 0 | O13: 0 | P13: =SUM(D13:O13) | Q13: =IFERROR(AVERAGE(D13:O13),0) | R13: =P13-C13*12
A14: TOTALE USCITE | C14: =SUM(C7:C13) | D14: =SUM(D7:D13) | E14: =SUM(E7:E13) | F14: =SUM(F7:F13) | G14: =SUM(G7:G13) | H14: =SUM(H7:H13) | I14: =SUM(I7:I13) | J14: =SUM(J7:J13) | ... O14: =SUM(O7:O13) | P14: =SUM(D14:O14) | Q14: =P14/12 | R14: =P14-C14*12
A15: SALDO | C15: =C6-C14 | D15: =D6-D14 | E15: =E6-E14 | F15: =F6-F14 | G15: =G6-G14 | H15: =H6-H14 | I15: =I6-I14 | J15: =J6-J14 | ... P15: =P6-P14 | Q15: =P15/12 | R15: =R6-R14

Sheet Riepilogo
A1: Riepilogo annuale
A3: Entrate dell'anno | B3: =Budget!P6
A4: Uscite dell'anno | B4: =Budget!P14
A5: Risparmio dell'anno | B5: =B3-B4
A6: Tasso di risparmio | B6: =IFERROR(B5/B3,0)
A7: Media entrate al mese | B7: =B3/12
A8: Media uscite al mese | B8: =B4/12
A10: Categoria | B10: Totale anno | C10: Media mese | D10: Quota uscite
A11: =Budget!A8 | B11: =Budget!P8 | C11: =IFERROR(B11/12,0) | D11: =IFERROR(B11/$B$4,0)
A12: =Budget!A9 | B12: =Budget!P9 | C12: =IFERROR(B12/12,0) | D12: =IFERROR(B12/$B$4,0)
A13: =Budget!A10 | B13: =Budget!P10 | C13: =IFERROR(B13/12,0) | D13: =IFERROR(B13/$B$4,0)
A14: =Budget!A11 | B14: =Budget!P11 | C14: =IFERROR(B14/12,0) | D14: =IFERROR(B14/$B$4,0)
A15: =Budget!A12 | B15: =Budget!P12 | C15: =IFERROR(B15/12,0) | D15: =IFERROR(B15/$B$4,0)
A16: =Budget!A13 | B16: =Budget!P13 | C16: =IFERROR(B16/12,0) | D16: =IFERROR(B16/$B$4,0)
A17: =Budget!A14 | B17: =Budget!P14 | C17: =IFERROR(B17/12,0) | D17: =IFERROR(B17/$B$4,0)
